{"ygPerms":{"resourceCapabilityList":[{"resourceType":"GROUP","capabilities":[{"name":"READ"},{"name":"JOIN"}]},{"resourceType":"PHOTO","capabilities":[]},{"resourceType":"FILE","capabilities":[]},{"resourceType":"MEMBER","capabilities":[]},{"resourceType":"LINK","capabilities":[]},{"resourceType":"CALENDAR","capabilities":[]},{"resourceType":"DATABASE","capabilities":[]},{"resourceType":"POLL","capabilities":[]},{"resourceType":"MESSAGE","capabilities":[{"name":"READ"}]},{"resourceType":"PENDING_MESSAGE","capabilities":[]},{"resourceType":"ATTACHMENTS","capabilities":[{"name":"READ"}]},{"resourceType":"PHOTOMATIC_ALBUMS","capabilities":[]},{"resourceType":"MEMBERSHIP_TYPE","capabilities":[]},{"resourceType":"POST","capabilities":[{"name":"READ"}]},{"resourceType":"PIN","capabilities":[]}],"groupUrl":"groups.yahoo.com","intlCode":"us"},"comscore":"pageview_candidate","ygData":{"userId":0,"authorName":"Karl Hatteland","from":"Karl Hatteland &lt;karlh@...&gt;","replyTo":"LIST","senderId":"KCMTxZ9OSFcfoqHa4d5nIR9u0ewfFMZkkXolUod4A2B3iqPwGEzdsEB-4BoPbaQOlHU6wkNuehgiWdyg6Q46kKIhHE87trFJbvg5-Q","spamInfo":{"isSpam":false,"reason":"0"},"subject":"Re: Spell Questions","postDate":"924375643","msgId":101,"canDelete":false,"contentTrasformed":false,"systemMessage":false,"headers":{"messageIdInHeader":"PDE1OTg3MC40LjEwMS45NTkyNzI1OTlAZUdyb3Vwcy5jb20+"},"prevInTopic":94,"nextInTopic":105,"prevInTime":100,"nextInTime":102,"topicId":35,"numMessagesInTopic":11,"msgSnippet":"Kast frost BOLT on a wall  :)","messageBody":"<div id=\"ygrps-yiv-727614223\">Kast frost BOLT on a wall  :)<br/>\n<br/>\n<a rel=\"nofollow\" target=\"_blank\" href=\"mailto:Bemeraroi@...\">Bemeraroi@...</a> wrote:<br/>\n<br/>\n<blockquote><span title=\"qreply\"> &gt; From: <a rel=\"nofollow\" target=\"_blank\" href=\"mailto:Bemeraroi@...\">Bemeraroi@...</a><br/>\n&gt;<br/>\n&gt; anyone know of a easy way to build of evoke other than hunting, like i<br/>\n&gt; usually built up my abjuration by casting shield alot.  and i curently use a<br/>\n&gt; dagger should i train in staffs 1 or 2 handed since i found a worn great<br/>\n&gt; staff on a skeleton?<br/>\n&gt;<br/>\n&gt; Samurai<br/>\n&gt;<br/>\n&gt; ------------------------------------------------------------------------<br/>\n&gt; Did you know that knowledge is power?<br/>\n&gt; <a rel=\"nofollow\" target=\"_blank\" href=\"http://www.ONElist.com\">http://www.ONElist.com</a><br/>\n&gt; Join a new ONElist e-mail community and strengthen your mind! </span></blockquote></div>","specialLinks":[]}}