{"ygPerms":{"resourceCapabilityList":[{"resourceType":"GROUP","capabilities":[{"name":"READ"},{"name":"JOIN"}]},{"resourceType":"PHOTO","capabilities":[]},{"resourceType":"FILE","capabilities":[]},{"resourceType":"MEMBER","capabilities":[]},{"resourceType":"LINK","capabilities":[]},{"resourceType":"CALENDAR","capabilities":[]},{"resourceType":"DATABASE","capabilities":[]},{"resourceType":"POLL","capabilities":[]},{"resourceType":"MESSAGE","capabilities":[{"name":"READ"}]},{"resourceType":"PENDING_MESSAGE","capabilities":[]},{"resourceType":"ATTACHMENTS","capabilities":[]},{"resourceType":"PHOTOMATIC_ALBUMS","capabilities":[]},{"resourceType":"MEMBERSHIP_TYPE","capabilities":[]},{"resourceType":"POST","capabilities":[{"name":"READ"}]},{"resourceType":"PIN","capabilities":[]}],"groupUrl":"groups.yahoo.com","intlCode":"us"},"comscore":"pageview_candidate","ygData":{"userId":0,"authorName":"Blitz Krieg","from":"&quot;Blitz Krieg&quot; &lt;blitz_krieg@...&gt;","replyTo":"LIST","senderId":"4_JYHku-W-jA0IvU3nXl794jchWevdARXcLaqzL_BB2d_-ZNkxe1bIQ9rBm1j0XjmaogRjn0q2cj_KicvmHBZywvpSPYqSNhFZjeuGtg","spamInfo":{"isSpam":false,"reason":"0"},"subject":"Re: Don&#39;t laugh at this question","postDate":"951687010","msgId":15475,"canDelete":false,"contentTrasformed":false,"systemMessage":false,"headers":{"messageIdInHeader":"PDE2MDg1MS43NzUuMTU0NzUuOTU5MjczMzg1QGVHcm91cHMuY29tPg=="},"prevInTopic":15452,"nextInTopic":15486,"prevInTime":15474,"nextInTime":15476,"topicId":15427,"numMessagesInTopic":13,"msgSnippet":"... Ogre bouncers, imo, have not been good experience. Darkfox Reven tsol Xegony","messageBody":"<div id=\"ygrps-yiv-467151806\"><blockquote><span title=\"ireply\">&gt; Would it just<br/>\n&gt; be better to join a group in one of the dungeons or kill ogre bouncers?<br/>\n&gt; <br/>\n&gt; Galtin of E&#39;ci<br/>\n<br/>\n </span></blockquote>Ogre bouncers, imo, have not been good experience.<br/>\n<br/>\nDarkfox Reven&#39;tsol<br/>\nXegony</div>","specialLinks":[]}}
