{"ygPerms":{"resourceCapabilityList":[{"resourceType":"GROUP","capabilities":[{"name":"READ"},{"name":"JOIN"}]},{"resourceType":"PHOTO","capabilities":[]},{"resourceType":"FILE","capabilities":[]},{"resourceType":"MEMBER","capabilities":[]},{"resourceType":"LINK","capabilities":[]},{"resourceType":"CALENDAR","capabilities":[]},{"resourceType":"DATABASE","capabilities":[]},{"resourceType":"POLL","capabilities":[]},{"resourceType":"MESSAGE","capabilities":[{"name":"READ"}]},{"resourceType":"PENDING_MESSAGE","capabilities":[]},{"resourceType":"ATTACHMENTS","capabilities":[]},{"resourceType":"PHOTOMATIC_ALBUMS","capabilities":[]},{"resourceType":"MEMBERSHIP_TYPE","capabilities":[]},{"resourceType":"POST","capabilities":[{"name":"READ"}]},{"resourceType":"PIN","capabilities":[]}],"groupUrl":"groups.yahoo.com","intlCode":"us"},"comscore":"pageview_candidate","ygData":{"userId":0,"authorName":"Rebecca Small","from":"&quot;Rebecca Small&quot; &lt;macha_nabaob@...&gt;","replyTo":"LIST","senderId":"Co7ki3tebw_JlgdgaypZ5224JM7qWN8mt8ikyrH4t8NRngaCbUSCUIdb0nbawyfjcPZ70wB0Wo4ilj5lxxKo6eDOWpu4zvjfhU3zQ5S3zX-M","spamInfo":{"isSpam":false,"reason":"0"},"subject":"But They raised the Bar!","postDate":"957884897","msgId":18426,"canDelete":false,"contentTrasformed":false,"systemMessage":false,"headers":{"messageIdInHeader":"PDIwMDAwNTA5MTUwODE3Ljg5OTUwLnFtYWlsQGhvdG1haWwuY29tPg=="},"prevInTopic":0,"nextInTopic":18427,"prevInTime":18425,"nextInTime":18427,"topicId":18426,"numMessagesInTopic":5,"msgSnippet":"Hail Fellow Tunesmiths, Kinda anti climatic now, but Ding! Welcome to L50. All I can say is get a group together and start on the first floor of Kedge at L35","messageBody":"<div id=\"ygrps-yiv-932329884\">Hail Fellow Tunesmiths,<br/>\n<br/>\nKinda anti climatic now, but Ding! Welcome to L50.<br/>\nAll I can say is get a group together and start on the first floor of Kedge <br/>\nat L35 or so, and work your way through as you level up. The loot sucks, but <br/>\nthe respawn rate makes this about the fastest experience place we have ever <br/>\nseen, and it&#39;s nearly always empty, even on Xegony.<br/>\n<br/>\nLady Brilinnia Ban&#39;Sidhe<br/>\nKnight Marshall, Order of the Rose<br/>\nExcalibur, Xegony<br/>\n<br/>\n________________________________________________________________________<br/>\nGet Your Private, Free E-mail from MSN Hotmail at <a rel=\"nofollow\" target=\"_blank\" href=\"http://www.hotmail.com\">http://www.hotmail.com</a></div>","specialLinks":[]}}
