{"ygPerms":{"resourceCapabilityList":[{"resourceType":"GROUP","capabilities":[{"name":"READ"},{"name":"JOIN"}]},{"resourceType":"PHOTO","capabilities":[]},{"resourceType":"FILE","capabilities":[]},{"resourceType":"MEMBER","capabilities":[]},{"resourceType":"LINK","capabilities":[]},{"resourceType":"CALENDAR","capabilities":[]},{"resourceType":"DATABASE","capabilities":[]},{"resourceType":"POLL","capabilities":[]},{"resourceType":"MESSAGE","capabilities":[{"name":"READ"}]},{"resourceType":"PENDING_MESSAGE","capabilities":[]},{"resourceType":"ATTACHMENTS","capabilities":[]},{"resourceType":"PHOTOMATIC_ALBUMS","capabilities":[]},{"resourceType":"MEMBERSHIP_TYPE","capabilities":[]},{"resourceType":"POST","capabilities":[{"name":"READ"}]},{"resourceType":"PIN","capabilities":[]}],"groupUrl":"groups.yahoo.com","intlCode":"us"},"comscore":"pageview_candidate","ygData":{"userId":0,"authorName":"Eric Chudej","from":"&quot;Eric Chudej&quot; &lt;Chudej@...","replyTo":"LIST","senderId":"PkUNhKUpBHlQp_QKMYoBS7rkAnslDgtWy3tPoQqxP7e4mZdKwyV90jAAnfhzAIN2vbRQmoUVeCZK6pWnRH35Z8YkdNMp1g","spamInfo":{"isSpam":false,"reason":"0"},"subject":"quest question","postDate":"866571140","msgId":2030,"canDelete":false,"contentTrasformed":false,"systemMessage":false,"headers":{"messageIdInHeader":"PDE2MDg1MS4xMTMuMjAzMC45NTkyNzMzNjlAZUdyb3Vwcy5jb20+"},"prevInTopic":0,"nextInTopic":2031,"prevInTime":2029,"nextInTime":2031,"topicId":2030,"numMessagesInTopic":13,"msgSnippet":"does anyone know if we can do the freeport corrupt guard quest with the charismatic carillion song??? if so is it worth doing???","messageBody":"<div id=\"ygrps-yiv-714249870\">does anyone know if we can do the freeport corrupt guard quest with the<br/>\ncharismatic carillion song???<br/>\n<br/>\nif so is it worth doing???</div>","specialLinks":[]}}
