{"ygPerms":{"resourceCapabilityList":[{"resourceType":"GROUP","capabilities":[{"name":"READ"},{"name":"JOIN"}]},{"resourceType":"PHOTO","capabilities":[]},{"resourceType":"FILE","capabilities":[]},{"resourceType":"MEMBER","capabilities":[]},{"resourceType":"LINK","capabilities":[]},{"resourceType":"CALENDAR","capabilities":[]},{"resourceType":"DATABASE","capabilities":[]},{"resourceType":"POLL","capabilities":[]},{"resourceType":"MESSAGE","capabilities":[{"name":"READ"}]},{"resourceType":"PENDING_MESSAGE","capabilities":[]},{"resourceType":"ATTACHMENTS","capabilities":[]},{"resourceType":"PHOTOMATIC_ALBUMS","capabilities":[]},{"resourceType":"MEMBERSHIP_TYPE","capabilities":[]},{"resourceType":"POST","capabilities":[{"name":"READ"}]},{"resourceType":"PIN","capabilities":[]}],"groupUrl":"groups.yahoo.com","intlCode":"us"},"comscore":"pageview_candidate","ygData":{"userId":0,"authorName":"JasonF","from":"&quot;JasonF&quot; &lt;JasonF@...","replyTo":"LIST","senderId":"Cw4QTURJSz1Oh8vAaU53YjeACBkGbgC7_H9Al4UJnXY5infGxAL7tXX6Lr9WUTuYs574WigQPEu8_DZ4thdc1r5mgpE","spamInfo":{"isSpam":false,"reason":"0"},"subject":"RE: Strange deaths in Mistmoore","postDate":"942276324","msgId":9848,"canDelete":false,"contentTrasformed":false,"systemMessage":false,"headers":{"messageIdInHeader":"PDE2MDg1MS40OTguOTg0OC45NTkyNzMzNzhAZUdyb3Vwcy5jb20+"},"prevInTopic":9845,"nextInTopic":9854,"prevInTime":9847,"nextInTime":9849,"topicId":9845,"numMessagesInTopic":6,"msgSnippet":"... Haha!  All of what I ve read about Mistmoore is correct, but when I read this I had to laugh.  Can you image the reaction of the mob in the castle? Hey,","messageBody":"<div id=\"ygrps-yiv-548943841\"><blockquote><span title=\"ireply\">&gt; The skeleton pet on<br/>\n&gt; the wrong side of the wall will not join in your fights at the<br/>\n&gt; zone unless you hit it first.<br/>\n&gt;<br/>\n&gt; --<br/>\n&gt; John H. Kim<br/>\n<br/>\n </span></blockquote>Haha!  All of what I&#39;ve read about Mistmoore is correct, but when I read<br/>\nthis I had to laugh.  Can you image the reaction of the mob in the castle?<br/>\n&quot;Hey, what the hell is this?  How is that mob way out by the zone able to<br/>\nhit my pet?  Bug!  Bug!&quot;<br/>\n<br/>\nCrier</div>","specialLinks":[]}}
