{"ygPerms":{"resourceCapabilityList":[{"resourceType":"GROUP","capabilities":[{"name":"READ"},{"name":"JOIN"}]},{"resourceType":"PHOTO","capabilities":[]},{"resourceType":"FILE","capabilities":[]},{"resourceType":"MEMBER","capabilities":[]},{"resourceType":"LINK","capabilities":[]},{"resourceType":"CALENDAR","capabilities":[]},{"resourceType":"DATABASE","capabilities":[]},{"resourceType":"POLL","capabilities":[]},{"resourceType":"MESSAGE","capabilities":[{"name":"READ"}]},{"resourceType":"PENDING_MESSAGE","capabilities":[]},{"resourceType":"ATTACHMENTS","capabilities":[{"name":"READ"}]},{"resourceType":"PHOTOMATIC_ALBUMS","capabilities":[]},{"resourceType":"MEMBERSHIP_TYPE","capabilities":[]},{"resourceType":"POST","capabilities":[{"name":"READ"}]},{"resourceType":"PIN","capabilities":[]}],"groupUrl":"groups.yahoo.com","intlCode":"us"},"comscore":"pageview_candidate","ygData":{"userId":0,"authorName":"Dan Kassiday","from":"&quot;Dan Kassiday&quot; &lt;kassiday@...","replyTo":"LIST","senderId":"Xk602WQQLNXYfLzqkT_dPw73qZiWRnuMoyYk13K1oVzFR-isYZz8uw-KZP_y01gNH2Iy3flVjOR1yqKBM2Q2uWUYrvQuSsTZcoPInX_qHA","spamInfo":{"isSpam":false,"reason":"0"},"subject":"Freeport search for holy sword","postDate":"924842347","msgId":75,"canDelete":false,"contentTrasformed":false,"systemMessage":false,"headers":{"messageIdInHeader":"PDE2MTU1My41Ljc1Ljk1OTI3Mzg2MUBlR3JvdXBzLmNvbT4="},"prevInTopic":0,"nextInTopic":0,"prevInTime":74,"nextInTime":76,"topicId":75,"numMessagesInTopic":1,"msgSnippet":"Thanks to all who provided hints on the quest that begins with the note to the agent in the militia. Once I have tracked down the fellow that is supposed to","messageBody":"<div id=\"ygrps-yiv-1270295226\">Thanks to all who provided hints on the quest that begins with the <br/>\nnote to the agent in the militia.<br/>\n<br/>\nOnce I have tracked down the fellow that is supposed to have done <br/>\naway with zimel, am I supposed to confront him?  or try and kill him <br/>\nand take his sword?  if it is to be battle how high a level do I need <br/>\nto be?  Or rather how strong is he?  so I can gather sufficient <br/>\nallies.  <br/>\n<br/>\nKhossidar of the Underfoot<br/>\nFenin Ro<br/>\nDan Kassiday<br/>\n<a rel=\"nofollow\" target=\"_blank\" href=\"http://www.clark.net/pub/kassiday\">http://www.clark.net/pub/kassiday</a><br/>\nreply to - <a rel=\"nofollow\" target=\"_blank\" href=\"mailto:kassiday@...\">kassiday@...</a></div>","specialLinks":[]}}