{"ygPerms":{"resourceCapabilityList":[{"resourceType":"GROUP","capabilities":[{"name":"READ"},{"name":"JOIN"}]},{"resourceType":"PHOTO","capabilities":[]},{"resourceType":"FILE","capabilities":[]},{"resourceType":"MEMBER","capabilities":[]},{"resourceType":"LINK","capabilities":[]},{"resourceType":"CALENDAR","capabilities":[]},{"resourceType":"DATABASE","capabilities":[]},{"resourceType":"POLL","capabilities":[]},{"resourceType":"MESSAGE","capabilities":[{"name":"READ"}]},{"resourceType":"PENDING_MESSAGE","capabilities":[]},{"resourceType":"ATTACHMENTS","capabilities":[{"name":"READ"}]},{"resourceType":"PHOTOMATIC_ALBUMS","capabilities":[]},{"resourceType":"MEMBERSHIP_TYPE","capabilities":[]},{"resourceType":"POST","capabilities":[{"name":"READ"}]},{"resourceType":"PIN","capabilities":[]}],"groupUrl":"groups.yahoo.com","intlCode":"us"},"comscore":"pageview_candidate","ygData":{"userId":0,"authorName":"John Carr","from":"John Carr &lt;jrcarr@...&gt;","replyTo":"LIST","senderId":"t2xISPzy5Zn40Epkw-9rz4IMUFuJZf342sZLNiKjVkzyCe-uKbxOYCrtUv-1-u2jW9crxTuVBEe33D_gfZZhk8Mj94-hHFQ","spamInfo":{"isSpam":false,"reason":"0"},"subject":"Gemcutter with various Velious gems","postDate":"996175932","msgId":2488,"canDelete":false,"contentTrasformed":false,"systemMessage":false,"headers":{"messageIdInHeader":"PDAwM2QwMWMxMTYwOSRhYjJhMDhlMCQ1OTgwNTA5MEBBRE1DMTAzNj4="},"prevInTopic":0,"nextInTopic":2489,"prevInTime":2487,"nextInTime":2489,"topicId":2488,"numMessagesInTopic":7,"msgSnippet":"Has anyone tried using the gemcutter along with various Velious gems to see if you could change the type of gem? For example, take a flawless aquamarine and","messageBody":"<div id=\"ygrps-yiv-434923716\">Has anyone tried using the gemcutter along with various Velious gems to see<br/>\nif you could change the type of gem?<br/>\n<br/>\nFor example, take a flawless aquamarine and gemcutter and combine in<br/>\nJewelers bag to see what happens?<br/>\n<br/>\nVelious gems seem to come in a variety of types (crushed,<br/>\nchipped,flawed,flawless and pristine)</div>","specialLinks":[]}}