{"ygPerms":{"resourceCapabilityList":[{"resourceType":"GROUP","capabilities":[{"name":"READ"},{"name":"JOIN"}]},{"resourceType":"PHOTO","capabilities":[]},{"resourceType":"FILE","capabilities":[]},{"resourceType":"MEMBER","capabilities":[]},{"resourceType":"LINK","capabilities":[]},{"resourceType":"CALENDAR","capabilities":[]},{"resourceType":"DATABASE","capabilities":[]},{"resourceType":"POLL","capabilities":[]},{"resourceType":"MESSAGE","capabilities":[{"name":"READ"}]},{"resourceType":"PENDING_MESSAGE","capabilities":[]},{"resourceType":"ATTACHMENTS","capabilities":[{"name":"READ"}]},{"resourceType":"PHOTOMATIC_ALBUMS","capabilities":[]},{"resourceType":"MEMBERSHIP_TYPE","capabilities":[]},{"resourceType":"POST","capabilities":[{"name":"READ"}]},{"resourceType":"PIN","capabilities":[]}],"groupUrl":"groups.yahoo.com","intlCode":"us"},"comscore":"pageview_candidate","ygData":{"userId":0,"authorName":"Joshua Bednarz","from":"&quot;Joshua Bednarz&quot; &lt;thewhitemage@...","replyTo":"LIST","senderId":"6xgB7538YsP14lAbmSMGNoNtPthQFCrgeTUV8kmas4ok8iHx5R7tj1aTkhqFvEHWH5jks9hOiwtvtIhmCTH6JfVUX81o30uUpcbpGP8_IhofhA","spamInfo":{"isSpam":false,"reason":"0"},"subject":"RE: lindel","postDate":"939078456","msgId":711,"canDelete":false,"contentTrasformed":false,"systemMessage":false,"headers":{"messageIdInHeader":"PDE1MDIwMi45OC43MTEuOTU5MjY1MzUwQGVHcm91cHMuY29tPg=="},"prevInTopic":710,"nextInTopic":712,"prevInTime":710,"nextInTime":712,"topicId":699,"numMessagesInTopic":18,"msgSnippet":"Nay, actually, when I want to be, I can get much of what I want. Thats how I even got him to give me a clue in the first place.","messageBody":"<div id=\"ygrps-yiv-1414043773\">Nay, actually, when I want to be, I can get much of what I want. Thats how I <br/>\neven got him to give me a clue in the first place.</div>","specialLinks":[]}}