{"ygPerms":{"resourceCapabilityList":[{"resourceType":"GROUP","capabilities":[{"name":"READ"},{"name":"JOIN"}]},{"resourceType":"PHOTO","capabilities":[]},{"resourceType":"FILE","capabilities":[]},{"resourceType":"MEMBER","capabilities":[]},{"resourceType":"LINK","capabilities":[]},{"resourceType":"CALENDAR","capabilities":[]},{"resourceType":"DATABASE","capabilities":[]},{"resourceType":"POLL","capabilities":[]},{"resourceType":"MESSAGE","capabilities":[{"name":"READ"}]},{"resourceType":"PENDING_MESSAGE","capabilities":[]},{"resourceType":"ATTACHMENTS","capabilities":[{"name":"READ"}]},{"resourceType":"PHOTOMATIC_ALBUMS","capabilities":[]},{"resourceType":"MEMBERSHIP_TYPE","capabilities":[]},{"resourceType":"POST","capabilities":[{"name":"READ"}]},{"resourceType":"PIN","capabilities":[]}],"groupUrl":"groups.yahoo.com","intlCode":"us"},"comscore":"pageview_candidate","ygData":{"userId":555548572,"authorName":"Carina Blankenship","from":"&quot;Carina Blankenship&quot; &lt;louisefacepg4@...&gt;","profile":"bridgespeyton713","replyTo":"LIST","senderId":"qZFm3wQfqgsHDWVFUoSkqWPJBS_m9gecDJzOOkrf0mcrExge1pWKPtpqjZpPmju2QjylB2IZpioBHeh6UoFrF8e_hpAwi_0sjZg1Yosb6OY-PQFYirJA","spamInfo":{"isSpam":false,"reason":"12"},"subject":"Is Fast To Find Sexy People!","postDate":"1387837346","msgId":4816,"canDelete":false,"contentTrasformed":false,"systemMessage":false,"headers":{"messageIdInHeader":"PDIzNzM0ODYyMzk3ODY5NDI2NkB5YWhvb2dyb3Vwcy5jb20+"},"prevInTopic":0,"nextInTopic":0,"prevInTime":4815,"nextInTime":4817,"topicId":4816,"numMessagesInTopic":1,"msgSnippet":"Get Closer To Matches Close To Your City For Secret Sex! Enjoy Photos Of Sex Mates In Your Town Sex Dating  http://2u.lc/CG5u","messageBody":"<div id=\"ygrps-yiv-946495922\">Get Closer To Matches Close To Your City For Secret Sex!<br/>\nEnjoy Photos Of Sex Mates In Your Town<br/>\n<br/>\nSex Dating &gt;&gt; <a rel=\"nofollow\" target=\"_blank\" href=\"http://2u.lc/CG5u\">http://2u.lc/CG5u</a></div>","specialLinks":[]}}