{"ygPerms":{"resourceCapabilityList":[{"resourceType":"GROUP","capabilities":[{"name":"READ"},{"name":"JOIN"}]},{"resourceType":"PHOTO","capabilities":[]},{"resourceType":"FILE","capabilities":[]},{"resourceType":"MEMBER","capabilities":[]},{"resourceType":"LINK","capabilities":[]},{"resourceType":"CALENDAR","capabilities":[]},{"resourceType":"DATABASE","capabilities":[]},{"resourceType":"POLL","capabilities":[]},{"resourceType":"MESSAGE","capabilities":[{"name":"READ"}]},{"resourceType":"PENDING_MESSAGE","capabilities":[]},{"resourceType":"ATTACHMENTS","capabilities":[{"name":"READ"}]},{"resourceType":"PHOTOMATIC_ALBUMS","capabilities":[]},{"resourceType":"MEMBERSHIP_TYPE","capabilities":[]},{"resourceType":"POST","capabilities":[{"name":"READ"}]},{"resourceType":"PIN","capabilities":[]}],"groupUrl":"groups.yahoo.com","intlCode":"us"},"comscore":"pageview_candidate","ygData":{"userId":555548572,"authorName":"Jan Whitham","from":"&quot;Jan Whitham&quot; &lt;louisefacepg4@...&gt;","profile":"bridgespeyton713","replyTo":"LIST","senderId":"aHnDNOwVPQTr_ORULuKX_PYzwggXXtUnj2HPmy1-8NvAP5XAKXdurWkpY8G4o-Y8qytwfAnBK0uiMJG7hCYKqsq8QGQvrGBCkuiLxPrH5to","spamInfo":{"isSpam":false,"reason":"12"},"subject":"On-line Amateur Peep Shows For Free Subscribers","postDate":"1390337557","msgId":5829,"canDelete":false,"contentTrasformed":false,"systemMessage":false,"headers":{"messageIdInHeader":"PDQyMjU2NzU5Njg1Mzk2Njc0QHlhaG9vZ3JvdXBzLmNvbT4="},"prevInTopic":0,"nextInTopic":0,"prevInTime":5828,"nextInTime":5830,"topicId":5829,"numMessagesInTopic":1,"msgSnippet":"Desperate To Join The Horniest On-line Cam Website? Take A Look On High Number Of Online Cams For Free Adult Video Cams  http://redir.ec/2GNIZ","messageBody":"<div id=\"ygrps-yiv-1220296425\">Desperate To Join The Horniest On-line Cam Website?<br/>\nTake A Look On High Number Of Online Cams For Free<br/>\n<br/>\nAdult Video Cams &gt;&gt;&gt; <a rel=\"nofollow\" target=\"_blank\" href=\"http://redir.ec/2GNIZ\">http://redir.ec/2GNIZ</a></div>","specialLinks":[]}}