{"ygPerms":{"resourceCapabilityList":[{"resourceType":"GROUP","capabilities":[{"name":"READ"},{"name":"JOIN"}]},{"resourceType":"PHOTO","capabilities":[]},{"resourceType":"FILE","capabilities":[]},{"resourceType":"MEMBER","capabilities":[]},{"resourceType":"LINK","capabilities":[]},{"resourceType":"CALENDAR","capabilities":[]},{"resourceType":"DATABASE","capabilities":[]},{"resourceType":"POLL","capabilities":[]},{"resourceType":"MESSAGE","capabilities":[{"name":"READ"}]},{"resourceType":"PENDING_MESSAGE","capabilities":[]},{"resourceType":"ATTACHMENTS","capabilities":[{"name":"READ"}]},{"resourceType":"PHOTOMATIC_ALBUMS","capabilities":[]},{"resourceType":"MEMBERSHIP_TYPE","capabilities":[]},{"resourceType":"POST","capabilities":[{"name":"READ"}]},{"resourceType":"PIN","capabilities":[]}],"groupUrl":"groups.yahoo.com","intlCode":"us"},"comscore":"pageview_candidate","ygData":{"userId":559382509,"authorName":"Jerome Mathews","from":"&quot;Jerome Mathews&quot; &lt;hallebadgerp61@...&gt;","profile":"peggywilliamsonjc84","replyTo":"LIST","senderId":"-mskn6DyX6QRmoYTZtH0KB2AcOoTScyAC5H2inbJ0vUOnz2BRnulMrCvqjjbCgrBNiT5u-Iuvs98q6ORcJHXEExRr0GXbVX4_vkQCld32Iei","spamInfo":{"isSpam":false,"reason":"12"},"subject":"Go Through Free Web Meeting","postDate":"1390783487","msgId":6104,"canDelete":false,"contentTrasformed":false,"systemMessage":false,"headers":{"messageIdInHeader":"PDY1MTgyMTUxMzc5NDIxMTM3QHlhaG9vZ3JvdXBzLmNvbT4="},"prevInTopic":0,"nextInTopic":0,"prevInTime":6103,"nextInTime":6105,"topicId":6104,"numMessagesInTopic":1,"msgSnippet":"Prepared To Experience Your Next Virtual Adult Encounter? Find Pictures Of Personals From The World Adult Dating  http://stos.me/415c","messageBody":"<div id=\"ygrps-yiv-103263966\">Prepared To Experience Your Next Virtual Adult Encounter?<br/>\nFind Pictures Of Personals From The World<br/>\n<br/>\nAdult Dating &gt;&gt; <a rel=\"nofollow\" target=\"_blank\" href=\"http://stos.me/415c\">http://stos.me/415c</a></div>","specialLinks":[]}}