{"ygPerms":{"resourceCapabilityList":[{"resourceType":"GROUP","capabilities":[{"name":"READ"},{"name":"JOIN"}]},{"resourceType":"PHOTO","capabilities":[]},{"resourceType":"FILE","capabilities":[]},{"resourceType":"MEMBER","capabilities":[]},{"resourceType":"LINK","capabilities":[]},{"resourceType":"CALENDAR","capabilities":[]},{"resourceType":"DATABASE","capabilities":[]},{"resourceType":"POLL","capabilities":[]},{"resourceType":"MESSAGE","capabilities":[{"name":"READ"}]},{"resourceType":"PENDING_MESSAGE","capabilities":[]},{"resourceType":"ATTACHMENTS","capabilities":[{"name":"READ"}]},{"resourceType":"PHOTOMATIC_ALBUMS","capabilities":[]},{"resourceType":"MEMBERSHIP_TYPE","capabilities":[]},{"resourceType":"POST","capabilities":[{"name":"READ"}]},{"resourceType":"PIN","capabilities":[]}],"groupUrl":"groups.yahoo.com","intlCode":"us"},"comscore":"pageview_candidate","ygData":{"userId":555548572,"authorName":"Rey Elder","from":"&quot;Rey Elder&quot; &lt;louisefacepg4@...&gt;","profile":"bridgespeyton713","replyTo":"LIST","senderId":"MUiFMa9QHD3Kr7bA33GV6gYAHxouRaL6iKrWvWa350C36ORZV86cyVKKlk42-0ZuATU8CbTsQlYMfwoS6p7J5zvzB4kgDig1jSay-9bl","spamInfo":{"isSpam":false,"reason":"12"},"subject":"Hook Up With A Fresh Love On Line This Night","postDate":"1395081671","msgId":8870,"canDelete":false,"contentTrasformed":false,"systemMessage":false,"headers":{"messageIdInHeader":"PDU0OTY2MzQ0MTgyMTgwOTY1MEB5YWhvb2dyb3Vwcy5jb20+"},"prevInTopic":8859,"nextInTopic":0,"prevInTime":8869,"nextInTime":8871,"topicId":8859,"numMessagesInTopic":2,"msgSnippet":"What Are You Waiting To Have A Chat With Sex Partners? 100% Free Online Matching And Matchmaking For Single Daters Hot Dating  http://merky.de/7452ad","messageBody":"<div id=\"ygrps-yiv-792429415\">What Are You Waiting To Have A Chat With Sex Partners?<br/>\n100% Free Online Matching And Matchmaking For Single Daters <br/>\n<br/>\nHot Dating &gt;&gt;&gt; <a rel=\"nofollow\" target=\"_blank\" href=\"http://merky.de/7452ad\">http://merky.de/7452ad</a></div>","specialLinks":[]}}