{"ygPerms":{"resourceCapabilityList":[{"resourceType":"GROUP","capabilities":[{"name":"READ"},{"name":"JOIN"}]},{"resourceType":"PHOTO","capabilities":[]},{"resourceType":"FILE","capabilities":[]},{"resourceType":"MEMBER","capabilities":[]},{"resourceType":"LINK","capabilities":[]},{"resourceType":"CALENDAR","capabilities":[]},{"resourceType":"DATABASE","capabilities":[]},{"resourceType":"POLL","capabilities":[]},{"resourceType":"MESSAGE","capabilities":[{"name":"READ"}]},{"resourceType":"PENDING_MESSAGE","capabilities":[]},{"resourceType":"ATTACHMENTS","capabilities":[{"name":"READ"}]},{"resourceType":"PHOTOMATIC_ALBUMS","capabilities":[]},{"resourceType":"MEMBERSHIP_TYPE","capabilities":[]},{"resourceType":"POST","capabilities":[{"name":"READ"}]},{"resourceType":"PIN","capabilities":[]}],"groupUrl":"groups.yahoo.com","intlCode":"us"},"comscore":"pageview_candidate","ygData":{"userId":559382509,"authorName":"Graciela Luc","from":"&quot;Graciela Luc&quot; &lt;hallebadgerp61@...&gt;","profile":"peggywilliamsonjc84","replyTo":"LIST","senderId":"a8k1kBfrI8n8drNfgeO0CI2JkjFj_1Z-po8pu6dn2zLm0jU4UQfFInp-U4sCk8-EGdQ4aK6LXjc4qJTqanqQiPx8ZRwy9QG8MP1v4ld_5Q","spamInfo":{"isSpam":false,"reason":"12"},"subject":"Find Free On Line Contacting","postDate":"1397364144","msgId":9675,"canDelete":false,"contentTrasformed":false,"systemMessage":false,"headers":{"messageIdInHeader":"PDYzNDcyNzI0MTMyNjc3Nzg2NUB5YWhvb2dyb3Vwcy5jb20+"},"prevInTopic":0,"nextInTopic":10866,"prevInTime":9674,"nextInTime":9676,"topicId":9675,"numMessagesInTopic":2,"msgSnippet":"Are You Searching For A Private Alternative To Hook Up With Engaged Daters? Live An Intimate Dating In Our On Line Community With Cheating Partners Adult","messageBody":"<div id=\"ygrps-yiv-644106600\">Are You Searching For A Private Alternative To Hook Up With Engaged Daters?<br/>\nLive An Intimate Dating In Our On Line Community With Cheating Partners<br/>\n<br/>\nAdult Dating &gt;&gt; <a rel=\"nofollow\" target=\"_blank\" href=\"http://bit.ly/1j2EZxW\">http://bit.ly/1j2EZxW</a></div>","specialLinks":[]}}