{"ygPerms":{"resourceCapabilityList":[{"resourceType":"GROUP","capabilities":[{"name":"READ"},{"name":"JOIN"}]},{"resourceType":"PHOTO","capabilities":[]},{"resourceType":"FILE","capabilities":[]},{"resourceType":"MEMBER","capabilities":[]},{"resourceType":"LINK","capabilities":[]},{"resourceType":"CALENDAR","capabilities":[]},{"resourceType":"DATABASE","capabilities":[]},{"resourceType":"POLL","capabilities":[]},{"resourceType":"MESSAGE","capabilities":[{"name":"READ"}]},{"resourceType":"PENDING_MESSAGE","capabilities":[]},{"resourceType":"ATTACHMENTS","capabilities":[{"name":"READ"}]},{"resourceType":"PHOTOMATIC_ALBUMS","capabilities":[]},{"resourceType":"MEMBERSHIP_TYPE","capabilities":[]},{"resourceType":"POST","capabilities":[{"name":"READ"}]},{"resourceType":"PIN","capabilities":[]}],"groupUrl":"groups.yahoo.com","intlCode":"us"},"comscore":"pageview_candidate","ygData":{"userId":0,"authorName":"Seamus McNeill","from":"Seamus McNeill &lt;smcneill@...","replyTo":"LIST","senderId":"YICMRKLL5cfqaYoe4a5354YFeC4cKjeOyDcn9FfyeRdwhP3X07ydc9zrysq5a9zR4hUqjhaNKapgvTX018kZ5eWlnydHIlEfXvj0Ag","spamInfo":{"isSpam":false,"reason":"0"},"subject":"Quests","postDate":"924889641","msgId":56,"canDelete":false,"contentTrasformed":false,"systemMessage":false,"headers":{"messageIdInHeader":"PDE2MTU4NS42LjU2Ljk1OTI3Mzg3N0BlR3JvdXBzLmNvbT4="},"prevInTopic":0,"nextInTopic":61,"prevInTime":55,"nextInTime":57,"topicId":56,"numMessagesInTopic":10,"msgSnippet":"Have any of you done the message to Freeport yet.  I talked with one of the Guild Masters in Neriak and he gave me a quest to talk to a spy in Freeport.  I","messageBody":"<div id=\"ygrps-yiv-1621132342\">Have any of you done the message to Freeport yet.  I talked with one of<br/>\nthe Guild Masters in Neriak and he gave me a quest to talk to a spy in<br/>\nFreeport.  I have been Freeport and even in the guild....and I can&#39;t seem<br/>\nto find the guy I&#39;m looking for...maybe I have the wrong name written down<br/>\nor something....Anyone else ever do this quest?<br/>\n<br/>\nKorm<br/>\n<br/>\np.s.  Yes Dark Elves can wander into Freeport....as long as the guards<br/>\n/CON as dubiously at least.</div>","specialLinks":[]}}