{"ygPerms":{"resourceCapabilityList":[{"resourceType":"GROUP","capabilities":[{"name":"READ"},{"name":"JOIN"}]},{"resourceType":"PHOTO","capabilities":[]},{"resourceType":"FILE","capabilities":[]},{"resourceType":"MEMBER","capabilities":[]},{"resourceType":"LINK","capabilities":[]},{"resourceType":"CALENDAR","capabilities":[]},{"resourceType":"DATABASE","capabilities":[]},{"resourceType":"POLL","capabilities":[]},{"resourceType":"MESSAGE","capabilities":[{"name":"READ"}]},{"resourceType":"PENDING_MESSAGE","capabilities":[]},{"resourceType":"ATTACHMENTS","capabilities":[{"name":"READ"}]},{"resourceType":"PHOTOMATIC_ALBUMS","capabilities":[]},{"resourceType":"MEMBERSHIP_TYPE","capabilities":[]},{"resourceType":"POST","capabilities":[{"name":"READ"}]},{"resourceType":"PIN","capabilities":[]}],"groupUrl":"groups.yahoo.com","intlCode":"us"},"comscore":"pageview_candidate","ygData":{"userId":555513697,"authorName":"Lillie Noble","from":"&quot;Lillie Noble&quot; &lt;gingerbiasotti@...&gt;","profile":"paynezoe760","replyTo":"LIST","senderId":"dGF27FKKHo5iMc-_UmU5ICVIVcsF8zcLRAMcCa03eqMEbh6C9LluX6ik9SZLkcPoYpGqqEZpBJf2XHPbzaHJVTgbjNZw_sGhDPomoCHkh9MBIA","spamInfo":{"isSpam":false,"reason":"12"},"subject":"Do You Want To Check Up On Who Is Connected Instantly?","postDate":"1389184834","msgId":8938,"canDelete":false,"contentTrasformed":false,"systemMessage":false,"headers":{"messageIdInHeader":"PDIwMDEwODczOTMzNjI5NTY0OEB5YWhvb2dyb3Vwcy5jb20+"},"prevInTopic":8184,"nextInTopic":13195,"prevInTime":8937,"nextInTime":8939,"topicId":8184,"numMessagesInTopic":3,"msgSnippet":"Are You Seeking A Real Passion, An Intimate Adventure Or A Companionship? Free On-line Hooking Up Service To Date Girls Sex Dating  http://du.cx/B0R","messageBody":"<div id=\"ygrps-yiv-812591956\">Are You Seeking A Real Passion, An Intimate Adventure Or A Companionship?<br/>\nFree On-line Hooking Up Service To Date Girls<br/>\n<br/>\nSex Dating &gt;&gt; <a rel=\"nofollow\" target=\"_blank\" href=\"http://du.cx/B0R\">http://du.cx/B0R</a></div>","specialLinks":[]}}