{"ygPerms":{"resourceCapabilityList":[{"resourceType":"GROUP","capabilities":[{"name":"READ"},{"name":"JOIN"}]},{"resourceType":"PHOTO","capabilities":[]},{"resourceType":"FILE","capabilities":[]},{"resourceType":"MEMBER","capabilities":[]},{"resourceType":"LINK","capabilities":[]},{"resourceType":"CALENDAR","capabilities":[]},{"resourceType":"DATABASE","capabilities":[]},{"resourceType":"POLL","capabilities":[]},{"resourceType":"MESSAGE","capabilities":[{"name":"READ"}]},{"resourceType":"PENDING_MESSAGE","capabilities":[]},{"resourceType":"ATTACHMENTS","capabilities":[{"name":"READ"}]},{"resourceType":"PHOTOMATIC_ALBUMS","capabilities":[]},{"resourceType":"MEMBERSHIP_TYPE","capabilities":[]},{"resourceType":"POST","capabilities":[{"name":"READ"}]},{"resourceType":"PIN","capabilities":[]}],"groupUrl":"groups.yahoo.com","intlCode":"us"},"comscore":"pageview_candidate","ygData":{"userId":0,"authorName":"John_Miewald@PlayStation.Sony.Com","from":"John_Miewald@...","replyTo":"LIST","senderId":"BsMaLkIKvum4osteyDG0xW6jWwzo37Ir_GvQa87TgttK5kuBAIyVuU2eMHKrqXShhSKIU_JCMFH9mpUuaiquBEd2fZUXzEpx","spamInfo":{"isSpam":false,"reason":"0"},"subject":"Re: [EverQuest] Hi, I am new & stupid :)","postDate":"990566413","msgId":1434,"canDelete":false,"contentTrasformed":false,"systemMessage":false,"headers":{"messageIdInHeader":"PE9GQzA5RTI1ODUuMDNEMThCMUMtT044ODI1NkE1NC4wMDczM0JDMUBwbGF5c3RhdGlvbi5zb255LmNvbT4="},"prevInTopic":1433,"nextInTopic":1441,"prevInTime":1433,"nextInTime":1435,"topicId":1427,"numMessagesInTopic":16,"msgSnippet":"Thanks for the feedback everyone.","messageBody":"<div id=\"ygrps-yiv-529237701\">Thanks for the feedback everyone.</div>","specialLinks":[]}}