{"ygPerms":{"resourceCapabilityList":[{"resourceType":"GROUP","capabilities":[{"name":"READ"},{"name":"JOIN"}]},{"resourceType":"PHOTO","capabilities":[]},{"resourceType":"FILE","capabilities":[]},{"resourceType":"MEMBER","capabilities":[]},{"resourceType":"LINK","capabilities":[]},{"resourceType":"CALENDAR","capabilities":[]},{"resourceType":"DATABASE","capabilities":[]},{"resourceType":"POLL","capabilities":[]},{"resourceType":"MESSAGE","capabilities":[{"name":"READ"}]},{"resourceType":"PENDING_MESSAGE","capabilities":[]},{"resourceType":"ATTACHMENTS","capabilities":[{"name":"READ"}]},{"resourceType":"PHOTOMATIC_ALBUMS","capabilities":[]},{"resourceType":"MEMBERSHIP_TYPE","capabilities":[]},{"resourceType":"POST","capabilities":[{"name":"READ"}]},{"resourceType":"PIN","capabilities":[]}],"groupUrl":"groups.yahoo.com","intlCode":"us"},"comscore":"pageview_candidate","ygData":{"userId":0,"authorName":"lanceboggs@yahoo.com","from":"lanceboggs@...","replyTo":"LIST","senderId":"Fzkvth0jkm-dBbpTj2t_zmScJSITyccYDSYrhv9YiPNm9g59VqP5yNVhEJcGmFIT4c7CrD0UaadcCno","spamInfo":{"isSpam":false,"reason":"0"},"subject":"Re: Greetings all","postDate":"982968944","msgId":921,"canDelete":false,"contentTrasformed":false,"systemMessage":false,"headers":{"messageIdInHeader":"PDk3NnBwZyt2cTUxQGVHcm91cHMuY29tPg==","inReplyToHeader":"PERGNjQ1MzZEOERFOUQzMTFBQkY3MDAwMEY0QTI4NDE1MDE2QUY5QTFAbHBkNHViZDAxLmF1c3Rpbi5uYXZ5Lm1pbD4="},"prevInTopic":920,"nextInTopic":922,"prevInTime":920,"nextInTime":922,"topicId":916,"numMessagesInTopic":21,"msgSnippet":"On Fennin Ro Server Slithkar Reaperofsouls lvl 30 Iksar Necromancer ","messageBody":"<div id=\"ygrps-yiv-1031355626\">On Fennin Ro Server<br/>\n<br/>\nSlithkar Reaperofsouls lvl 30 Iksar Necromancer &lt;Harbringers of <br/>\nDespair&gt;<br/>\n<br/>\n<br/>\n--- In EverQuest@y..., &quot;IT3 Adam J. Daingerfield&quot; &lt;persona@a...&gt; <br/>\nwrote:<br/>\n<blockquote><span title=\"qreply\"> &gt; Just signing in for the first time...<br/>\n&gt; <br/>\n&gt; About me....<br/>\n&gt; <br/>\n&gt; On the Bertoxx server I have :<br/>\n&gt; level 13 bard &quot;Orcha&quot;<br/>\n&gt; level 12 monk &quot;Dainger&quot;<br/>\n&gt; and a few other low level ones </span></blockquote></div>","specialLinks":[]}}