{"ygPerms":{"resourceCapabilityList":[{"resourceType":"GROUP","capabilities":[{"name":"READ"},{"name":"JOIN"}]},{"resourceType":"PHOTO","capabilities":[]},{"resourceType":"FILE","capabilities":[]},{"resourceType":"MEMBER","capabilities":[]},{"resourceType":"LINK","capabilities":[]},{"resourceType":"CALENDAR","capabilities":[]},{"resourceType":"DATABASE","capabilities":[]},{"resourceType":"POLL","capabilities":[]},{"resourceType":"MESSAGE","capabilities":[{"name":"READ"}]},{"resourceType":"PENDING_MESSAGE","capabilities":[]},{"resourceType":"ATTACHMENTS","capabilities":[{"name":"READ"}]},{"resourceType":"PHOTOMATIC_ALBUMS","capabilities":[]},{"resourceType":"MEMBERSHIP_TYPE","capabilities":[]},{"resourceType":"POST","capabilities":[{"name":"READ"}]},{"resourceType":"PIN","capabilities":[]}],"groupUrl":"groups.yahoo.com","intlCode":"us"},"comscore":"pageview_candidate","ygData":{"userId":0,"authorName":"wolfie","from":"wolfie &lt;lachdanan@...","replyTo":"LIST","senderId":"7C2y2pv7I080ePBtBerW2jupw9zf1ZgaX6SQbp7UixDlC8wl-LCSMWC5AGmEULozY_inzD3qBoQVhqcWyQQeb45mBVR0iw","spamInfo":{"isSpam":false,"reason":"0"},"subject":"DOT and Unkempt Druids","postDate":"938349226","msgId":1314,"canDelete":false,"contentTrasformed":false,"systemMessage":false,"headers":{"messageIdInHeader":"PDE2MDk1Ni4xNDUuMTMxNC45NTkyNzM0NTFAZUdyb3Vwcy5jb20+"},"prevInTopic":0,"nextInTopic":0,"prevInTime":1313,"nextInTime":1315,"topicId":1314,"numMessagesInTopic":1,"msgSnippet":"I use the L29 set of DOT spells and want to know how much damage they do and how long does it take or how long before casting again?  I refer to stacking 3;","messageBody":"<div id=\"ygrps-yiv-83238837\">I use the L29 set of DOT spells and want to know how much damage they do<br/>\nand how long does it take or how long before casting again?  I refer to<br/>\nstacking 3; BB, ES, VC.<br/>\n<br/>\nWhere, exactly, are the Unkept Druids in Rathe Mtns?<br/>\n<br/>\nSmakin<br/>\nL30 Necro<br/>\nPovar</div>","specialLinks":[]}}
