{"ygPerms":{"resourceCapabilityList":[{"resourceType":"GROUP","capabilities":[{"name":"READ"},{"name":"JOIN"}]},{"resourceType":"PHOTO","capabilities":[]},{"resourceType":"FILE","capabilities":[]},{"resourceType":"MEMBER","capabilities":[]},{"resourceType":"LINK","capabilities":[]},{"resourceType":"CALENDAR","capabilities":[]},{"resourceType":"DATABASE","capabilities":[]},{"resourceType":"POLL","capabilities":[]},{"resourceType":"MESSAGE","capabilities":[{"name":"READ"}]},{"resourceType":"PENDING_MESSAGE","capabilities":[]},{"resourceType":"ATTACHMENTS","capabilities":[{"name":"READ"}]},{"resourceType":"PHOTOMATIC_ALBUMS","capabilities":[]},{"resourceType":"MEMBERSHIP_TYPE","capabilities":[]},{"resourceType":"POST","capabilities":[{"name":"READ"}]},{"resourceType":"PIN","capabilities":[]}],"groupUrl":"groups.yahoo.com","intlCode":"us"},"comscore":"pageview_candidate","ygData":{"userId":37568490,"authorName":"KAZ","from":"KAZ &lt;kazvorpal@...&gt;","profile":"KAZVorpal","replyTo":"LIST","senderId":"M37Lnh1GRb-6tC2SheL2Lh99eZz_Cw9nG10LPFuUO9kvN21WuUJNvE0doPFichh_dSmYwbWJSf21oz_-CsPw","spamInfo":{"isSpam":false,"reason":"0"},"subject":"Re: [EQ_Necromancer] Hello I&#39;m New","postDate":"1051217322","msgId":2345,"canDelete":false,"contentTrasformed":false,"systemMessage":false,"headers":{"messageIdInHeader":"PDIwMDMwNDI0MjA0ODQyLjUyNzA1LnFtYWlsQHdlYjQxNTA0Lm1haWwueWFob28uY29tPg==","inReplyToHeader":"PGI4OTU0OCs2YmVkQGVHcm91cHMuY29tPg=="},"prevInTopic":2344,"nextInTopic":0,"prevInTime":2344,"nextInTime":2346,"topicId":2344,"numMessagesInTopic":2,"msgSnippet":"... Necromancers are the best, for soloing. Even with the Fear nerf, they re also the best for surviving on PvP servers...most of the cowardly Player Killers","messageBody":"<div id=\"ygrps-yiv-978379558\">--- Beverly &lt;<a rel=\"nofollow\" target=\"_blank\" href=\"mailto:beverlyreed2002@...\">beverlyreed2002@...</a>&gt; wrote:<br/>\n<blockquote><span title=\"ireply\"> &gt; I think the title of the subject says it all. I&#39;ve been playing EQ a <br/>\n&gt; little over four years now. I have recently fallen in love with my <br/>\n&gt; Necromancer. &quot;Justene Thyme&quot; is lvl 35 now and I&#39;ve been playing her <br/>\n&gt; a lot more than my Druid that I at one loved the most. <br/>\n<br/>\n </span></blockquote>Necromancers are the best, for soloing.<br/>\n<br/>\nEven with the Fear nerf, they&#39;re also the best for surviving on PvP<br/>\nservers...most of the cowardly Player Killers have a much harder time<br/>\nsneak-attacking Necromancers successfully. They&#39;ve one of the best pets, and<br/>\ncan kill an attacking player faster with their DoTs than even a wizard with<br/>\nhis mana-hogging DDs.<br/>\n<br/>\n--<br/>\nWords of the Sentient:<br/>\n<br/>\nDon&#39;t join the book burners. Don&#39;t think you are going to conceal<br/>\nfaults by concealing evidence that they ever existed. -- Dwight D. Eisenhower<br/>\n<br/>\n=====<br/>\nThe government that seems the most unwise,<br/>\n   Most goodness to the people supplies;<br/>\n   That which is tampers, touching everything,<br/>\n   Will work but ill, and disappointment bring.<br/>\n                          -- Tao Te Ching<br/>\nAIM/Yahoo/AOL Instant Messenger: KazVorpal    <br/>\nICQ#: 1912557 MSN Messenger: <a rel=\"nofollow\" target=\"_blank\" href=\"mailto:KazVorpal@...\">KazVorpal@...</a></div>","specialLinks":[]}}
